{
  "$schema": "https://developer.microsoft.com/json-schemas/fabric/item/report/definition/visualContainer/2.10.0/schema.json",
  "name": "c0c26927be291ead6793",
  "position": {
    "x": 9.72644376899696,
    "y": 0,
    "z": 1000,
    "height": 47.659574468085111,
    "width": 1047.5379939209727,
    "tabOrder": 0
  },
  "visual": {
    "visualType": "textbox",
    "objects": {
      "general": [
        {
          "properties": {
            "paragraphs": [
              {
                "textRuns": [
                  {
                    "value": "Executive Overview: Tech Giants AI Investment Benchmark (2015 - 2024)",
                    "textStyle": {
                      "fontWeight": "bold",
                      "fontSize": "20pt",
                      "textDecoration": "underline"
                    }
                  }
                ],
                "horizontalTextAlignment": "center"
              }
            ]
          }
        }
      ]
    },
    "drillFilterOtherVisuals": true
  }
}